POP/Embedder.py
POP/LLMClient.py
POP/POP.py
POP/__init__.py
POP/prompts/2024-11-19-content_finder.md
POP/prompts/2024-11-19-get_content.md
POP/prompts/2024-11-19-get_title_and_url.md
POP/prompts/CLI_AI_helper.md
POP/prompts/content_finder.md
POP/prompts/corpus_splitter.md
POP/prompts/fabric-improve_prompt.md
POP/prompts/function_code_generator.md
POP/prompts/function_description_generator.md
POP/prompts/get_content.md
POP/prompts/get_title_and_url.md
POP/prompts/json_formatter_prompt.md
POP/prompts/openai-function_description_generator.md
POP/prompts/openai-json_schema_generator.md
POP/prompts/openai-prompt_generator.md
POP/schemas/biomedical_ner_extractor.json
POP/schemas/entity_extraction_per_sentence.json
pop_python-1.0.4.dist-info/licenses/LICENSE
pop_python-1.0.4.dist-info/METADATA
pop_python-1.0.4.dist-info/WHEEL
pop_python-1.0.4.dist-info/top_level.txt
pop_python-1.0.4.dist-info/RECORD
